my_package/mymodule.py
qwq_package/mymodule.py
qwq_package-0.1.0.dist-info/METADATA
qwq_package-0.1.0.dist-info/WHEEL
qwq_package-0.1.0.dist-info/top_level.txt
qwq_package-0.1.0.dist-info/RECORD
