Metadata-Version: 2.1
Name: qwq-package
Version: 0.1.0
Summary: A short description of mylibrary
Author: wenqiang
Author-email: qwqhhjx@163.com
Classifier: Development Status :: 3 - Alpha
Classifier: Intended Audience :: Developers
Classifier: License :: OSI Approved :: MIT License
Classifier: Programming Language :: Python :: 3
Classifier: Programming Language :: Python :: 3.6
Classifier: Programming Language :: Python :: 3.7
Classifier: Programming Language :: Python :: 3.8
Classifier: Programming Language :: Python :: 3.9
Requires-Dist: pandas (~=1.5.0)
